{
    "Apple": [
        {
            "model": "Apple iPhone 5",
            "price": 75.00,
            "image": "http://dport96.github.io/ITM352/morea/080.flow-control-II/iphone-3gs.jpg"
        }
    ],
    "Samsung": [
        {
            "model": "Samsung Galaxy Note 7",
            "price": 75.00,
            "image": "http://dport96.github.io/ITM352/morea/080.flow-control-II/Samsung.jpg"
        },
        {
            "model": "Samsung Galaxy Note 8",
            "price": 85.00,
            "image": "http://dport96.github.io/ITM352/morea/080.flow-control-II/Samsung.jpg"
        }
    ], 
    "Others":  
    [
        {
            "model": "HTC",
            "price": 40.00,
            "image": "http://dport96.github.io/ITM352/morea/080.flow-control-II/HTC.jpg"
        },
        {
            "model": "Nokia",
            "price": 35.00,
            "image": "http://dport96.github.io/ITM352/morea/080.flow-control-II/Nokia.jpg"
        },
        {
            "model": "Blackberry",
            "price": 10.00,
            "image": "http://dport96.github.io/ITM352/morea/080.flow-control-II/Blackberry.jpg"
        }
    ]
}